udg/cli.py
udg/common.py
udg/entropydg.py
udg/nodaldg.py
udg/quadratures.py
udg/semdg.py
udg/upwinddg.py
udg-0.1.1.dist-info/METADATA
udg-0.1.1.dist-info/WHEEL
udg-0.1.1.dist-info/entry_points.txt
udg-0.1.1.dist-info/licenses/LICENSE
udg-0.1.1.dist-info/RECORD
