Metadata-Version: 2.4
Name: udg
Version: 0.1.1
Summary: Upwind summation-by-parts discontinuous galerkin method for solving PDEs
License-File: LICENSE
Requires-Python: <3.13,>=3.11
Requires-Dist: click>=8.1
Requires-Dist: matplotlib>=3.7
Requires-Dist: mpltools>=0.2.0
Requires-Dist: numpy>=1.26.0
Requires-Dist: scipy>=1.10
Provides-Extra: dev
Requires-Dist: mypy>=1.19.0; extra == 'dev'
Requires-Dist: pre-commit>=4.5.1; extra == 'dev'
Requires-Dist: pytest-xdist>=3.5.0; extra == 'dev'
Requires-Dist: pytest>=8.3.4; extra == 'dev'
Requires-Dist: ruff>=0.14.8; extra == 'dev'
